{
    "foreground_intensity_properties_per_channel": {
        "0": {
            "max": 150.48052978515625,
            "mean": 2.193206548690796,
            "median": 1.7534902095794678,
            "min": 1.0,
            "percentile_00_5": 1.0031359195709229,
            "percentile_99_5": 14.393611598014928,
            "std": 1.988387942314148
        },
        "1": {
            "max": 3071.0,
            "mean": 67.15141296386719,
            "median": 40.0,
            "min": -3024.0,
            "percentile_00_5": -1000.0,
            "percentile_99_5": 1039.0,
            "std": 188.75750732421875
        }
    },
    "median_relative_size_after_cropping": 1.0,
    "shapes_after_crop": [
        [
            324,
            200,
            200
        ],
        [
            384,
            200,
            200
        ],
        [
            354,
            200,
            200
        ],
        [
            486,
            440,
            440
        ],
        [
            520,
            440,
            440
        ],
        [
            669,
            440,
            440
        ],
        [
            404,
            440,
            440
        ],
        [
            324,
            168,
            168
        ],
        [
            374,
            168,
            168
        ],
        [
            391,
            440,
            440
        ],
        [
            421,
            440,
            440
        ],
        [
            382,
            440,
            440
        ],
        [
            432,
            440,
            440
        ],
        [
            429,
            440,
            440
        ],
        [
            424,
            168,
            168
        ],
        [
            428,
            440,
            440
        ],
        [
            444,
            440,
            440
        ],
        [
            445,
            440,
            440
        ],
        [
            440,
            440,
            440
        ],
        [
            432,
            440,
            440
        ],
        [
            432,
            440,
            440
        ],
        [
            324,
            168,
            168
        ],
        [
            403,
            440,
            440
        ],
        [
            324,
            168,
            168
        ],
        [
            503,
            440,
            440
        ],
        [
            380,
            440,
            440
        ],
        [
            436,
            440,
            440
        ],
        [
            475,
            440,
            440
        ],
        [
            408,
            440,
            440
        ],
        [
            421,
            440,
            440
        ],
        [
            405,
            440,
            440
        ],
        [
            521,
            440,
            440
        ],
        [
            374,
            168,
            168
        ],
        [
            388,
            440,
            440
        ],
        [
            419,
            440,
            440
        ],
        [
            424,
            168,
            168
        ],
        [
            416,
            440,
            440
        ],
        [
            324,
            168,
            168
        ],
        [
            371,
            128,
            128
        ],
        [
            407,
            192,
            192
        ],
        [
            407,
            192,
            192
        ],
        [
            335,
            192,
            192
        ],
        [
            407,
            192,
            192
        ],
        [
            407,
            192,
            192
        ],
        [
            299,
            192,
            192
        ],
        [
            407,
            192,
            192
        ],
        [
            335,
            192,
            192
        ],
        [
            335,
            192,
            192
        ],
        [
            299,
            192,
            192
        ],
        [
            335,
            192,
            192
        ],
        [
            407,
            192,
            192
        ],
        [
            479,
            192,
            192
        ],
        [
            335,
            192,
            192
        ],
        [
            335,
            192,
            192
        ],
        [
            335,
            192,
            192
        ],
        [
            479,
            192,
            192
        ],
        [
            335,
            192,
            192
        ],
        [
            407,
            192,
            192
        ],
        [
            335,
            192,
            192
        ],
        [
            335,
            192,
            192
        ],
        [
            443,
            192,
            192
        ],
        [
            335,
            192,
            192
        ],
        [
            299,
            192,
            192
        ],
        [
            335,
            192,
            192
        ],
        [
            299,
            192,
            192
        ],
        [
            335,
            192,
            192
        ],
        [
            335,
            192,
            192
        ],
        [
            335,
            192,
            192
        ],
        [
            407,
            192,
            192
        ],
        [
            407,
            192,
            192
        ],
        [
            299,
            192,
            192
        ],
        [
            335,
            192,
            192
        ],
        [
            407,
            192,
            192
        ],
        [
            335,
            192,
            192
        ],
        [
            407,
            192,
            192
        ],
        [
            335,
            192,
            192
        ],
        [
            407,
            192,
            192
        ],
        [
            299,
            192,
            192
        ],
        [
            335,
            192,
            192
        ],
        [
            335,
            192,
            192
        ],
        [
            335,
            192,
            192
        ],
        [
            335,
            192,
            192
        ],
        [
            335,
            192,
            192
        ],
        [
            335,
            192,
            192
        ],
        [
            299,
            192,
            192
        ],
        [
            371,
            192,
            192
        ],
        [
            407,
            192,
            192
        ],
        [
            299,
            192,
            192
        ],
        [
            335,
            192,
            192
        ],
        [
            335,
            192,
            192
        ],
        [
            335,
            192,
            192
        ],
        [
            407,
            192,
            192
        ],
        [
            299,
            192,
            192
        ],
        [
            335,
            192,
            192
        ],
        [
            335,
            192,
            192
        ],
        [
            335,
            192,
            192
        ],
        [
            335,
            192,
            192
        ],
        [
            335,
            192,
            192
        ],
        [
            335,
            192,
            192
        ],
        [
            551,
            192,
            192
        ],
        [
            407,
            192,
            192
        ],
        [
            335,
            192,
            192
        ],
        [
            335,
            192,
            192
        ],
        [
            335,
            192,
            192
        ],
        [
            299,
            192,
            192
        ],
        [
            407,
            192,
            192
        ],
        [
            335,
            192,
            192
        ],
        [
            407,
            192,
            192
        ],
        [
            299,
            192,
            192
        ],
        [
            263,
            192,
            192
        ],
        [
            299,
            192,
            192
        ],
        [
            299,
            192,
            192
        ],
        [
            335,
            192,
            192
        ],
        [
            335,
            192,
            192
        ],
        [
            335,
            192,
            192
        ],
        [
            407,
            192,
            192
        ],
        [
            335,
            192,
            192
        ],
        [
            335,
            192,
            192
        ],
        [
            407,
            192,
            192
        ],
        [
            299,
            192,
            192
        ],
        [
            371,
            192,
            192
        ],
        [
            335,
            192,
            192
        ],
        [
            335,
            192,
            192
        ],
        [
            335,
            192,
            192
        ],
        [
            407,
            192,
            192
        ],
        [
            407,
            192,
            192
        ],
        [
            335,
            192,
            192
        ],
        [
            335,
            192,
            192
        ],
        [
            335,
            192,
            192
        ],
        [
            335,
            192,
            192
        ],
        [
            299,
            192,
            192
        ],
        [
            335,
            192,
            192
        ],
        [
            335,
            192,
            192
        ],
        [
            335,
            192,
            192
        ],
        [
            299,
            192,
            192
        ],
        [
            335,
            192,
            192
        ],
        [
            335,
            192,
            192
        ],
        [
            407,
            192,
            192
        ],
        [
            407,
            192,
            192
        ],
        [
            335,
            192,
            192
        ],
        [
            299,
            192,
            192
        ],
        [
            335,
            192,
            192
        ],
        [
            299,
            192,
            192
        ],
        [
            299,
            192,
            192
        ],
        [
            335,
            192,
            192
        ],
        [
            407,
            192,
            192
        ],
        [
            335,
            192,
            192
        ],
        [
            335,
            192,
            192
        ],
        [
            335,
            192,
            192
        ],
        [
            335,
            192,
            192
        ],
        [
            407,
            192,
            192
        ],
        [
            407,
            192,
            192
        ],
        [
            407,
            192,
            192
        ],
        [
            335,
            192,
            192
        ],
        [
            335,
            192,
            192
        ],
        [
            335,
            192,
            192
        ],
        [
            335,
            192,
            192
        ],
        [
            407,
            192,
            192
        ],
        [
            335,
            192,
            192
        ],
        [
            335,
            192,
            192
        ],
        [
            299,
            192,
            192
        ],
        [
            407,
            192,
            192
        ],
        [
            335,
            192,
            192
        ],
        [
            443,
            192,
            192
        ],
        [
            407,
            192,
            192
        ],
        [
            407,
            192,
            192
        ],
        [
            335,
            192,
            192
        ],
        [
            407,
            192,
            192
        ],
        [
            407,
            192,
            192
        ],
        [
            407,
            192,
            192
        ],
        [
            443,
            192,
            192
        ],
        [
            371,
            192,
            192
        ],
        [
            407,
            192,
            192
        ],
        [
            299,
            192,
            192
        ],
        [
            515,
            192,
            192
        ],
        [
            407,
            192,
            192
        ],
        [
            335,
            192,
            192
        ],
        [
            407,
            192,
            192
        ],
        [
            335,
            192,
            192
        ],
        [
            299,
            192,
            192
        ],
        [
            299,
            192,
            192
        ],
        [
            335,
            192,
            192
        ],
        [
            335,
            192,
            192
        ],
        [
            299,
            192,
            192
        ],
        [
            371,
            192,
            192
        ],
        [
            335,
            192,
            192
        ],
        [
            299,
            192,
            192
        ],
        [
            299,
            192,
            192
        ],
        [
            299,
            192,
            192
        ],
        [
            335,
            192,
            192
        ],
        [
            299,
            192,
            192
        ],
        [
            335,
            192,
            192
        ],
        [
            335,
            192,
            192
        ],
        [
            335,
            192,
            192
        ],
        [
            515,
            192,
            192
        ],
        [
            335,
            192,
            192
        ],
        [
            407,
            192,
            192
        ],
        [
            371,
            192,
            192
        ],
        [
            335,
            192,
            192
        ],
        [
            299,
            192,
            192
        ],
        [
            335,
            192,
            192
        ],
        [
            299,
            192,
            192
        ],
        [
            407,
            192,
            192
        ],
        [
            335,
            192,
            192
        ],
        [
            335,
            192,
            192
        ],
        [
            335,
            192,
            192
        ],
        [
            335,
            192,
            192
        ],
        [
            371,
            192,
            192
        ],
        [
            335,
            192,
            192
        ],
        [
            299,
            192,
            192
        ],
        [
            551,
            192,
            192
        ],
        [
            299,
            192,
            192
        ],
        [
            335,
            192,
            192
        ],
        [
            335,
            192,
            192
        ],
        [
            335,
            192,
            192
        ],
        [
            335,
            192,
            192
        ],
        [
            299,
            192,
            192
        ],
        [
            299,
            192,
            192
        ],
        [
            335,
            192,
            192
        ],
        [
            299,
            192,
            192
        ],
        [
            335,
            192,
            192
        ],
        [
            335,
            192,
            192
        ],
        [
            335,
            192,
            192
        ],
        [
            335,
            192,
            192
        ],
        [
            299,
            192,
            192
        ],
        [
            299,
            192,
            192
        ],
        [
            335,
            192,
            192
        ],
        [
            335,
            192,
            192
        ],
        [
            335,
            192,
            192
        ],
        [
            335,
            192,
            192
        ],
        [
            335,
            192,
            192
        ],
        [
            335,
            256,
            256
        ],
        [
            371,
            256,
            256
        ],
        [
            299,
            192,
            192
        ],
        [
            503,
            256,
            256
        ],
        [
            449,
            256,
            256
        ],
        [
            449,
            256,
            256
        ],
        [
            721,
            200,
            200
        ],
        [
            379,
            200,
            200
        ],
        [
            355,
            200,
            200
        ],
        [
            739,
            200,
            200
        ],
        [
            404,
            200,
            200
        ],
        [
            394,
            200,
            200
        ],
        [
            371,
            200,
            200
        ],
        [
            371,
            200,
            200
        ],
        [
            362,
            200,
            200
        ],
        [
            358,
            200,
            200
        ],
        [
            415,
            200,
            200
        ],
        [
            383,
            200,
            200
        ],
        [
            367,
            200,
            200
        ],
        [
            213,
            200,
            200
        ],
        [
            222,
            200,
            200
        ],
        [
            244,
            200,
            200
        ],
        [
            276,
            200,
            200
        ],
        [
            244,
            200,
            200
        ],
        [
            244,
            200,
            200
        ],
        [
            244,
            200,
            200
        ],
        [
            244,
            200,
            200
        ],
        [
            276,
            200,
            200
        ],
        [
            453,
            200,
            200
        ],
        [
            500,
            200,
            200
        ],
        [
            488,
            200,
            200
        ],
        [
            532,
            200,
            200
        ],
        [
            384,
            512,
            512
        ],
        [
            492,
            200,
            200
        ],
        [
            522,
            200,
            200
        ],
        [
            913,
            200,
            200
        ],
        [
            382,
            512,
            512
        ],
        [
            423,
            200,
            200
        ],
        [
            903,
            200,
            200
        ],
        [
            413,
            440,
            440
        ],
        [
            205,
            128,
            128
        ],
        [
            360,
            169,
            169
        ],
        [
            255,
            144,
            144
        ],
        [
            255,
            169,
            169
        ],
        [
            360,
            169,
            169
        ],
        [
            276,
            144,
            144
        ],
        [
            234,
            144,
            144
        ],
        [
            318,
            169,
            169
        ],
        [
            254,
            144,
            144
        ],
        [
            412,
            180,
            180
        ],
        [
            323,
            180,
            180
        ],
        [
            323,
            180,
            180
        ],
        [
            323,
            180,
            180
        ],
        [
            323,
            180,
            180
        ],
        [
            322,
            440,
            440
        ],
        [
            352,
            180,
            180
        ],
        [
            351,
            440,
            440
        ],
        [
            323,
            180,
            180
        ],
        [
            323,
            180,
            180
        ],
        [
            199,
            200,
            200
        ],
        [
            196,
            200,
            200
        ],
        [
            207,
            200,
            200
        ],
        [
            441,
            200,
            200
        ],
        [
            382,
            200,
            200
        ],
        [
            720,
            180,
            180
        ],
        [
            747,
            180,
            180
        ],
        [
            339,
            200,
            200
        ],
        [
            1206,
            180,
            180
        ],
        [
            202,
            200,
            200
        ],
        [
            382,
            200,
            200
        ],
        [
            412,
            200,
            200
        ],
        [
            285,
            200,
            200
        ],
        [
            363,
            200,
            200
        ],
        [
            683,
            180,
            180
        ],
        [
            332,
            200,
            200
        ],
        [
            370,
            200,
            200
        ],
        [
            222,
            200,
            200
        ],
        [
            708,
            440,
            440
        ],
        [
            359,
            200,
            200
        ],
        [
            217,
            200,
            200
        ],
        [
            706,
            440,
            440
        ],
        [
            627,
            440,
            440
        ],
        [
            697,
            440,
            440
        ],
        [
            363,
            200,
            200
        ],
        [
            711,
            440,
            440
        ],
        [
            323,
            200,
            200
        ],
        [
            382,
            200,
            200
        ],
        [
            352,
            180,
            180
        ],
        [
            323,
            180,
            180
        ],
        [
            267,
            128,
            128
        ],
        [
            213,
            150,
            150
        ],
        [
            299,
            128,
            128
        ],
        [
            488,
            200,
            200
        ],
        [
            449,
            256,
            256
        ],
        [
            449,
            256,
            256
        ],
        [
            395,
            256,
            256
        ]
    ],
    "spacings": [
        [
            3.0,
            4.0728302001953125,
            4.0728302001953125
        ],
        [
            3.0,
            4.0728302001953125,
            4.0728302001953125
        ],
        [
            3.0,
            4.0728302001953125,
            4.0728302001953125
        ],
        [
            2.5,
            1.649999976158142,
            1.649999976158142
        ],
        [
            2.5,
            1.649999976158142,
            1.649999976158142
        ],
        [
            1.5,
            1.649999976158142,
            1.649999976158142
        ],
        [
            2.5,
            1.649999976158142,
            1.649999976158142
        ],
        [
            3.0,
            3.3940300941467285,
            3.3940300941467285
        ],
        [
            3.0,
            3.3940300941467285,
            3.3940300941467285
        ],
        [
            2.5,
            1.649999976158142,
            1.649999976158142
        ],
        [
            2.5,
            1.649999976158142,
            1.649999976158142
        ],
        [
            2.5,
            1.649999976158142,
            1.649999976158142
        ],
        [
            2.5,
            1.649999976158142,
            1.649999976158142
        ],
        [
            2.5,
            1.649999976158142,
            1.649999976158142
        ],
        [
            3.0,
            3.3940300941467285,
            3.3940300941467285
        ],
        [
            2.5,
            1.649999976158142,
            1.649999976158142
        ],
        [
            2.5,
            1.649999976158142,
            1.649999976158142
        ],
        [
            2.5,
            1.649999976158142,
            1.649999976158142
        ],
        [
            2.5,
            1.649999976158142,
            1.649999976158142
        ],
        [
            2.5,
            1.649999976158142,
            1.649999976158142
        ],
        [
            2.5,
            1.649999976158142,
            1.649999976158142
        ],
        [
            3.0,
            3.3940300941467285,
            3.3940300941467285
        ],
        [
            2.5,
            1.649999976158142,
            1.649999976158142
        ],
        [
            3.0,
            3.3940300941467285,
            3.3940300941467285
        ],
        [
            2.5,
            1.649999976158142,
            1.649999976158142
        ],
        [
            2.5,
            1.649999976158142,
            1.649999976158142
        ],
        [
            2.5,
            1.649999976158142,
            1.649999976158142
        ],
        [
            2.5,
            1.649999976158142,
            1.649999976158142
        ],
        [
            2.5,
            1.649999976158142,
            1.649999976158142
        ],
        [
            2.5,
            1.649999976158142,
            1.649999976158142
        ],
        [
            2.5,
            1.649999976158142,
            1.649999976158142
        ],
        [
            2.5,
            1.649999976158142,
            1.649999976158142
        ],
        [
            3.0,
            3.3940300941467285,
            3.3940300941467285
        ],
        [
            2.5,
            1.649999976158142,
            1.649999976158142
        ],
        [
            2.5,
            1.649999976158142,
            1.649999976158142
        ],
        [
            3.0,
            3.3940300941467285,
            3.3940300941467285
        ],
        [
            2.5,
            1.649999976158142,
            1.649999976158142
        ],
        [
            3.0,
            3.3940300941467285,
            3.3940300941467285
        ],
        [
            3.2699999809265137,
            5.46875,
            5.46875
        ],
        [
            3.2699999809265137,
            2.8645832538604736,
            2.8645832538604736
        ],
        [
            3.2699999809265137,
            2.8645832538604736,
            2.8645832538604736
        ],
        [
            3.2700002193450928,
            2.8645832538604736,
            2.8645832538604736
        ],
        [
            3.2699999809265137,
            2.8645832538604736,
            2.8645832538604736
        ],
        [
            3.2699999809265137,
            2.8645832538604736,
            2.8645832538604736
        ],
        [
            3.2699999809265137,
            2.8645832538604736,
            2.8645832538604736
        ],
        [
            3.2699999809265137,
            2.8645832538604736,
            2.8645832538604736
        ],
        [
            3.2700002193450928,
            2.8645832538604736,
            2.8645832538604736
        ],
        [
            3.2700002193450928,
            3.6458332538604736,
            3.6458332538604736
        ],
        [
            3.2699999809265137,
            2.8645832538604736,
            2.8645832538604736
        ],
        [
            3.2700002193450928,
            2.8645832538604736,
            2.8645832538604736
        ],
        [
            3.2699999809265137,
            2.8645832538604736,
            2.8645832538604736
        ],
        [
            3.2700002193450928,
            2.8645832538604736,
            2.8645832538604736
        ],
        [
            3.2700002193450928,
            2.8645832538604736,
            2.8645832538604736
        ],
        [
            3.2700002193450928,
            2.8645832538604736,
            2.8645832538604736
        ],
        [
            3.2700002193450928,
            2.8645832538604736,
            2.8645832538604736
        ],
        [
            3.2700002193450928,
            2.8645832538604736,
            2.8645832538604736
        ],
        [
            3.2700002193450928,
            3.6458332538604736,
            3.6458332538604736
        ],
        [
            3.2699999809265137,
            2.8645832538604736,
            2.8645832538604736
        ],
        [
            3.2700002193450928,
            2.8645832538604736,
            2.8645832538604736
        ],
        [
            3.2700002193450928,
            2.8645832538604736,
            2.8645832538604736
        ],
        [
            3.2700002193450928,
            2.8645832538604736,
            2.8645832538604736
        ],
        [
            3.2700002193450928,
            3.6458332538604736,
            3.6458332538604736
        ],
        [
            3.2699999809265137,
            2.8645832538604736,
            2.8645832538604736
        ],
        [
            3.2700002193450928,
            2.8645832538604736,
            2.8645832538604736
        ],
        [
            3.2699999809265137,
            2.8645832538604736,
            2.8645832538604736
        ],
        [
            3.2700002193450928,
            3.6458332538604736,
            3.6458332538604736
        ],
        [
            3.2700002193450928,
            2.8645832538604736,
            2.8645832538604736
        ],
        [
            3.2700002193450928,
            2.8645832538604736,
            2.8645832538604736
        ],
        [
            3.2699999809265137,
            2.8645832538604736,
            2.8645832538604736
        ],
        [
            3.2699999809265137,
            2.8645832538604736,
            2.8645832538604736
        ],
        [
            3.2699999809265137,
            3.6458332538604736,
            3.6458332538604736
        ],
        [
            3.2700002193450928,
            2.8645832538604736,
            2.8645832538604736
        ],
        [
            3.2699999809265137,
            2.8645832538604736,
            2.8645832538604736
        ],
        [
            3.2700002193450928,
            2.8645832538604736,
            2.8645832538604736
        ],
        [
            3.2699999809265137,
            3.6458332538604736,
            3.6458332538604736
        ],
        [
            3.2700002193450928,
            2.8645832538604736,
            2.8645832538604736
        ],
        [
            3.2699999809265137,
            2.8645832538604736,
            2.8645832538604736
        ],
        [
            3.2699999809265137,
            2.8645832538604736,
            2.8645832538604736
        ],
        [
            3.2700002193450928,
            2.8645832538604736,
            2.8645832538604736
        ],
        [
            3.2700002193450928,
            2.8645832538604736,
            2.8645832538604736
        ],
        [
            3.2700002193450928,
            2.8645832538604736,
            2.8645832538604736
        ],
        [
            3.2700002193450928,
            2.8645832538604736,
            2.8645832538604736
        ],
        [
            3.2700002193450928,
            2.8645832538604736,
            2.8645832538604736
        ],
        [
            3.2700002193450928,
            2.8645832538604736,
            2.8645832538604736
        ],
        [
            3.2699999809265137,
            2.8645832538604736,
            2.8645832538604736
        ],
        [
            3.2699999809265137,
            3.6458332538604736,
            3.6458332538604736
        ],
        [
            3.2699999809265137,
            2.8645832538604736,
            2.8645832538604736
        ],
        [
            3.2699999809265137,
            2.8645832538604736,
            2.8645832538604736
        ],
        [
            3.2700002193450928,
            2.8645832538604736,
            2.8645832538604736
        ],
        [
            3.2700002193450928,
            2.8645832538604736,
            2.8645832538604736
        ],
        [
            3.2700002193450928,
            2.8645832538604736,
            2.8645832538604736
        ],
        [
            3.2699999809265137,
            2.8645832538604736,
            2.8645832538604736
        ],
        [
            3.2699999809265137,
            2.8645832538604736,
            2.8645832538604736
        ],
        [
            3.2700002193450928,
            2.8645832538604736,
            2.8645832538604736
        ],
        [
            3.2700002193450928,
            2.8645832538604736,
            2.8645832538604736
        ],
        [
            3.2700002193450928,
            3.6458332538604736,
            3.6458332538604736
        ],
        [
            3.2700002193450928,
            2.8645832538604736,
            2.8645832538604736
        ],
        [
            3.2700002193450928,
            2.8645832538604736,
            2.8645832538604736
        ],
        [
            3.2700002193450928,
            2.8645832538604736,
            2.8645832538604736
        ],
        [
            3.2699999809265137,
            2.8645832538604736,
            2.8645832538604736
        ],
        [
            3.2699999809265137,
            3.6458332538604736,
            3.6458332538604736
        ],
        [
            3.2700002193450928,
            2.8645832538604736,
            2.8645832538604736
        ],
        [
            3.2700002193450928,
            3.6458332538604736,
            3.6458332538604736
        ],
        [
            3.2700002193450928,
            2.8645832538604736,
            2.8645832538604736
        ],
        [
            3.2699999809265137,
            2.8645832538604736,
            2.8645832538604736
        ],
        [
            3.2699999809265137,
            3.6458332538604736,
            3.6458332538604736
        ],
        [
            3.2700002193450928,
            2.8645832538604736,
            2.8645832538604736
        ],
        [
            3.2699999809265137,
            2.8645832538604736,
            2.8645832538604736
        ],
        [
            3.2699999809265137,
            2.8645832538604736,
            2.8645832538604736
        ],
        [
            3.2699999809265137,
            2.8645832538604736,
            2.8645832538604736
        ],
        [
            3.2699999809265137,
            2.8645832538604736,
            2.8645832538604736
        ],
        [
            3.2699999809265137,
            2.8645832538604736,
            2.8645832538604736
        ],
        [
            3.2700002193450928,
            2.8645832538604736,
            2.8645832538604736
        ],
        [
            3.2700002193450928,
            2.8645832538604736,
            2.8645832538604736
        ],
        [
            3.2700002193450928,
            2.8645832538604736,
            2.8645832538604736
        ],
        [
            3.2699999809265137,
            3.6458332538604736,
            3.6458332538604736
        ],
        [
            3.2700002193450928,
            2.8645832538604736,
            2.8645832538604736
        ],
        [
            3.2700002193450928,
            2.8645832538604736,
            2.8645832538604736
        ],
        [
            3.2699999809265137,
            2.8645832538604736,
            2.8645832538604736
        ],
        [
            3.2699999809265137,
            2.8645832538604736,
            2.8645832538604736
        ],
        [
            3.2699999809265137,
            2.8645832538604736,
            2.8645832538604736
        ],
        [
            3.2700002193450928,
            2.8645832538604736,
            2.8645832538604736
        ],
        [
            3.2700002193450928,
            2.8645832538604736,
            2.8645832538604736
        ],
        [
            3.2700002193450928,
            2.8645832538604736,
            2.8645832538604736
        ],
        [
            3.2699999809265137,
            3.6458332538604736,
            3.6458332538604736
        ],
        [
            3.2699999809265137,
            2.8645832538604736,
            2.8645832538604736
        ],
        [
            3.2700002193450928,
            2.8645832538604736,
            2.8645832538604736
        ],
        [
            3.2700002193450928,
            2.8645832538604736,
            2.8645832538604736
        ],
        [
            3.2700002193450928,
            2.8645832538604736,
            2.8645832538604736
        ],
        [
            3.2700002193450928,
            2.8645832538604736,
            2.8645832538604736
        ],
        [
            3.2699999809265137,
            3.6458332538604736,
            3.6458332538604736
        ],
        [
            3.2700002193450928,
            2.8645832538604736,
            2.8645832538604736
        ],
        [
            3.2700002193450928,
            3.6458332538604736,
            3.6458332538604736
        ],
        [
            3.2700002193450928,
            2.8645832538604736,
            2.8645832538604736
        ],
        [
            3.2699999809265137,
            2.8645832538604736,
            2.8645832538604736
        ],
        [
            3.2700002193450928,
            2.8645832538604736,
            2.8645832538604736
        ],
        [
            3.2700002193450928,
            2.8645832538604736,
            2.8645832538604736
        ],
        [
            3.2699999809265137,
            3.6458332538604736,
            3.6458332538604736
        ],
        [
            3.2699999809265137,
            3.6458332538604736,
            3.6458332538604736
        ],
        [
            3.2700002193450928,
            2.8645832538604736,
            2.8645832538604736
        ],
        [
            3.2699999809265137,
            3.6458332538604736,
            3.6458332538604736
        ],
        [
            3.2700002193450928,
            2.8645832538604736,
            2.8645832538604736
        ],
        [
            3.2699999809265137,
            2.8645832538604736,
            2.8645832538604736
        ],
        [
            3.2699999809265137,
            2.8645832538604736,
            2.8645832538604736
        ],
        [
            3.2700002193450928,
            2.8645832538604736,
            2.8645832538604736
        ],
        [
            3.2699999809265137,
            3.6458332538604736,
            3.6458332538604736
        ],
        [
            3.2700002193450928,
            3.6458332538604736,
            3.6458332538604736
        ],
        [
            3.2700002193450928,
            2.8645832538604736,
            2.8645832538604736
        ],
        [
            3.2700002193450928,
            3.6458332538604736,
            3.6458332538604736
        ],
        [
            3.2700002193450928,
            3.6458332538604736,
            3.6458332538604736
        ],
        [
            3.2699999809265137,
            2.8645832538604736,
            2.8645832538604736
        ],
        [
            3.2699999809265137,
            2.8645832538604736,
            2.8645832538604736
        ],
        [
            3.2699999809265137,
            3.6458332538604736,
            3.6458332538604736
        ],
        [
            3.2700002193450928,
            2.8645832538604736,
            2.8645832538604736
        ],
        [
            3.2700002193450928,
            3.6458332538604736,
            3.6458332538604736
        ],
        [
            3.2700002193450928,
            2.8645832538604736,
            2.8645832538604736
        ],
        [
            3.2700002193450928,
            3.6458332538604736,
            3.6458332538604736
        ],
        [
            3.2699999809265137,
            2.8645832538604736,
            2.8645832538604736
        ],
        [
            3.2700002193450928,
            2.8645832538604736,
            2.8645832538604736
        ],
        [
            3.2700002193450928,
            2.8645832538604736,
            2.8645832538604736
        ],
        [
            3.2699999809265137,
            2.8645832538604736,
            2.8645832538604736
        ],
        [
            3.2699999809265137,
            2.8645832538604736,
            2.8645832538604736
        ],
        [
            3.2700002193450928,
            3.6458332538604736,
            3.6458332538604736
        ],
        [
            3.2700002193450928,
            2.8645832538604736,
            2.8645832538604736
        ],
        [
            3.2699999809265137,
            2.8645832538604736,
            2.8645832538604736
        ],
        [
            3.2699999809265137,
            2.8645832538604736,
            2.8645832538604736
        ],
        [
            3.2700002193450928,
            2.8645832538604736,
            2.8645832538604736
        ],
        [
            3.2699999809265137,
            3.6458332538604736,
            3.6458332538604736
        ],
        [
            3.2699999809265137,
            2.8645832538604736,
            2.8645832538604736
        ],
        [
            3.2699999809265137,
            2.8645832538604736,
            2.8645832538604736
        ],
        [
            3.2699999809265137,
            2.8645832538604736,
            2.8645832538604736
        ],
        [
            3.2699999809265137,
            2.8645832538604736,
            2.8645832538604736
        ],
        [
            3.2699999809265137,
            2.8645832538604736,
            2.8645832538604736
        ],
        [
            3.2699999809265137,
            2.8645832538604736,
            2.8645832538604736
        ],
        [
            3.2699999809265137,
            2.8645832538604736,
            2.8645832538604736
        ],
        [
            3.2699999809265137,
            2.8645832538604736,
            2.8645832538604736
        ],
        [
            3.2700002193450928,
            2.8645832538604736,
            2.8645832538604736
        ],
        [
            3.2699999809265137,
            2.8645832538604736,
            2.8645832538604736
        ],
        [
            3.2700002193450928,
            2.8645832538604736,
            2.8645832538604736
        ],
        [
            3.2699999809265137,
            2.8645832538604736,
            2.8645832538604736
        ],
        [
            3.2699999809265137,
            2.8645832538604736,
            2.8645832538604736
        ],
        [
            3.2700002193450928,
            2.8645832538604736,
            2.8645832538604736
        ],
        [
            3.2700002193450928,
            2.8645832538604736,
            2.8645832538604736
        ],
        [
            3.2699999809265137,
            3.6458332538604736,
            3.6458332538604736
        ],
        [
            3.2699999809265137,
            2.8645832538604736,
            2.8645832538604736
        ],
        [
            3.2700002193450928,
            3.6458332538604736,
            3.6458332538604736
        ],
        [
            3.2699999809265137,
            2.8645832538604736,
            2.8645832538604736
        ],
        [
            3.2699999809265137,
            2.8645832538604736,
            2.8645832538604736
        ],
        [
            3.2699999809265137,
            3.6458332538604736,
            3.6458332538604736
        ],
        [
            3.2700002193450928,
            2.8645832538604736,
            2.8645832538604736
        ],
        [
            3.2699999809265137,
            2.8645832538604736,
            2.8645832538604736
        ],
        [
            3.2700002193450928,
            2.8645832538604736,
            2.8645832538604736
        ],
        [
            3.2700002193450928,
            2.8645832538604736,
            2.8645832538604736
        ],
        [
            3.2700002193450928,
            2.8645832538604736,
            2.8645832538604736
        ],
        [
            3.2699999809265137,
            2.8645832538604736,
            2.8645832538604736
        ],
        [
            3.2700002193450928,
            3.6458332538604736,
            3.6458332538604736
        ],
        [
            3.2699999809265137,
            2.8645832538604736,
            2.8645832538604736
        ],
        [
            3.2699999809265137,
            2.8645832538604736,
            2.8645832538604736
        ],
        [
            3.2700002193450928,
            2.8645832538604736,
            2.8645832538604736
        ],
        [
            3.2699999809265137,
            2.8645832538604736,
            2.8645832538604736
        ],
        [
            3.2700002193450928,
            2.8645832538604736,
            2.8645832538604736
        ],
        [
            3.2699999809265137,
            2.8645832538604736,
            2.8645832538604736
        ],
        [
            3.2699999809265137,
            2.8645832538604736,
            2.8645832538604736
        ],
        [
            3.2700002193450928,
            2.8645832538604736,
            2.8645832538604736
        ],
        [
            3.2700002193450928,
            2.8645832538604736,
            2.8645832538604736
        ],
        [
            3.2700002193450928,
            2.8645832538604736,
            2.8645832538604736
        ],
        [
            3.2700002193450928,
            2.8645832538604736,
            2.8645832538604736
        ],
        [
            3.2699999809265137,
            2.8645832538604736,
            2.8645832538604736
        ],
        [
            3.2700002193450928,
            2.8645832538604736,
            2.8645832538604736
        ],
        [
            3.2699999809265137,
            2.8645832538604736,
            2.8645832538604736
        ],
        [
            3.2699999809265137,
            2.8645832538604736,
            2.8645832538604736
        ],
        [
            3.2699999809265137,
            2.8645832538604736,
            2.8645832538604736
        ],
        [
            3.2700002193450928,
            2.8645832538604736,
            2.8645832538604736
        ],
        [
            3.2700002193450928,
            2.8645832538604736,
            2.8645832538604736
        ],
        [
            3.2700002193450928,
            3.6458332538604736,
            3.6458332538604736
        ],
        [
            3.2700002193450928,
            2.8645832538604736,
            2.8645832538604736
        ],
        [
            3.2699999809265137,
            2.8645832538604736,
            2.8645832538604736
        ],
        [
            3.2699999809265137,
            2.8645832538604736,
            2.8645832538604736
        ],
        [
            3.2700002193450928,
            2.8645832538604736,
            2.8645832538604736
        ],
        [
            3.2699999809265137,
            2.8645832538604736,
            2.8645832538604736
        ],
        [
            3.2700002193450928,
            2.8645832538604736,
            2.8645832538604736
        ],
        [
            3.2700002193450928,
            2.8645832538604736,
            2.8645832538604736
        ],
        [
            3.2700002193450928,
            2.8645832538604736,
            2.8645832538604736
        ],
        [
            3.2700002193450928,
            2.8645832538604736,
            2.8645832538604736
        ],
        [
            3.2699999809265137,
            2.8645832538604736,
            2.8645832538604736
        ],
        [
            3.2699999809265137,
            2.8645832538604736,
            2.8645832538604736
        ],
        [
            3.2700002193450928,
            2.8645832538604736,
            2.8645832538604736
        ],
        [
            3.2700002193450928,
            2.8645832538604736,
            2.8645832538604736
        ],
        [
            3.2700002193450928,
            2.8645832538604736,
            2.8645832538604736
        ],
        [
            3.2700002193450928,
            2.8645832538604736,
            2.8645832538604736
        ],
        [
            3.2700002193450928,
            2.8645832538604736,
            2.8645832538604736
        ],
        [
            3.2700002193450928,
            2.734375,
            2.734375
        ],
        [
            3.2699999809265137,
            2.734375,
            2.734375
        ],
        [
            3.2699999809265137,
            2.8645832538604736,
            2.8645832538604736
        ],
        [
            2.7900002002716064,
            2.734375,
            2.734375
        ],
        [
            2.7899999618530273,
            2.734375,
            2.734375
        ],
        [
            2.7900002002716064,
            2.734375,
            2.734375
        ],
        [
            2.5,
            4.0728302001953125,
            4.0728302001953125
        ],
        [
            2.5,
            4.0728302001953125,
            4.0728302001953125
        ],
        [
            2.5,
            4.0728302001953125,
            4.0728302001953125
        ],
        [
            2.5,
            4.0728302001953125,
            4.0728302001953125
        ],
        [
            2.5,
            4.0728302001953125,
            4.0728302001953125
        ],
        [
            2.5,
            4.0728302001953125,
            4.0728302001953125
        ],
        [
            2.5,
            4.0728302001953125,
            4.0728302001953125
        ],
        [
            2.5,
            4.0728302001953125,
            4.0728302001953125
        ],
        [
            2.5,
            4.0728302001953125,
            4.0728302001953125
        ],
        [
            2.5,
            4.0728302001953125,
            4.0728302001953125
        ],
        [
            2.5,
            4.0728302001953125,
            4.0728302001953125
        ],
        [
            2.5,
            4.0728302001953125,
            4.0728302001953125
        ],
        [
            5.0,
            4.0728302001953125,
            4.0728302001953125
        ],
        [
            5.0,
            4.0728302001953125,
            4.0728302001953125
        ],
        [
            5.0,
            4.0728302001953125,
            4.0728302001953125
        ],
        [
            4.0,
            4.0728302001953125,
            4.0728302001953125
        ],
        [
            4.0,
            4.0728302001953125,
            4.0728302001953125
        ],
        [
            4.0,
            4.0728302001953125,
            4.0728302001953125
        ],
        [
            4.0,
            4.0728302001953125,
            4.0728302001953125
        ],
        [
            4.0,
            4.0728302001953125,
            4.0728302001953125
        ],
        [
            4.0,
            4.0728302001953125,
            4.0728302001953125
        ],
        [
            4.0,
            4.0728302001953125,
            4.0728302001953125
        ],
        [
            2.0,
            4.072840213775635,
            4.072840213775635
        ],
        [
            2.0,
            4.072840213775635,
            4.072840213775635
        ],
        [
            2.0,
            4.072840213775635,
            4.072840213775635
        ],
        [
            2.0,
            4.072840213775635,
            4.072840213775635
        ],
        [
            3.0,
            1.5909500122070312,
            1.5909500122070312
        ],
        [
            2.0,
            4.072840213775635,
            4.072840213775635
        ],
        [
            2.0,
            4.072840213775635,
            4.072840213775635
        ],
        [
            2.0,
            4.072840213775635,
            4.072840213775635
        ],
        [
            3.0,
            1.5909500122070312,
            1.5909500122070312
        ],
        [
            2.5,
            4.0728302001953125,
            4.0728302001953125
        ],
        [
            2.0,
            4.072840213775635,
            4.072840213775635
        ],
        [
            2.5,
            1.649999976158142,
            1.649999976158142
        ],
        [
            4.25,
            3.90625,
            3.90625
        ],
        [
            4.0,
            4.0,
            4.0
        ],
        [
            4.0,
            4.0,
            4.0
        ],
        [
            4.0,
            4.0,
            4.0
        ],
        [
            4.0,
            4.0,
            4.0
        ],
        [
            4.0,
            4.0,
            4.0
        ],
        [
            4.0,
            4.0,
            4.0
        ],
        [
            4.0,
            4.0,
            4.0
        ],
        [
            4.0,
            4.0,
            4.0
        ],
        [
            3.0,
            4.113920211791992,
            4.113920211791992
        ],
        [
            3.0,
            4.113920211791992,
            4.113920211791992
        ],
        [
            3.0,
            4.113920211791992,
            4.113920211791992
        ],
        [
            3.0,
            4.113920211791992,
            4.113920211791992
        ],
        [
            3.0,
            4.113920211791992,
            4.113920211791992
        ],
        [
            3.0,
            1.649999976158142,
            1.649999976158142
        ],
        [
            3.0,
            4.113920211791992,
            4.113920211791992
        ],
        [
            3.0,
            1.649999976158142,
            1.649999976158142
        ],
        [
            3.0,
            4.113920211791992,
            4.113920211791992
        ],
        [
            3.0,
            4.113920211791992,
            4.113920211791992
        ],
        [
            5.0,
            4.0728302001953125,
            4.0728302001953125
        ],
        [
            5.0,
            4.0728302001953125,
            4.0728302001953125
        ],
        [
            5.0,
            4.072840213775635,
            4.072840213775635
        ],
        [
            3.0,
            4.0728302001953125,
            4.0728302001953125
        ],
        [
            3.0,
            4.0728302001953125,
            4.0728302001953125
        ],
        [
            1.5,
            4.113920211791992,
            4.113920211791992
        ],
        [
            1.5,
            4.113920211791992,
            4.113920211791992
        ],
        [
            3.0,
            4.072840213775635,
            4.072840213775635
        ],
        [
            1.5,
            4.113920211791992,
            4.113920211791992
        ],
        [
            5.0,
            4.072840213775635,
            4.072840213775635
        ],
        [
            3.0,
            4.0728302001953125,
            4.0728302001953125
        ],
        [
            3.0,
            4.0728302001953125,
            4.0728302001953125
        ],
        [
            5.0,
            3.899998664855957,
            3.899998664855957
        ],
        [
            3.0,
            4.072840213775635,
            4.072840213775635
        ],
        [
            1.5,
            4.113920211791992,
            4.113920211791992
        ],
        [
            3.0,
            4.072840213775635,
            4.072840213775635
        ],
        [
            3.0,
            4.072840213775635,
            4.072840213775635
        ],
        [
            5.0,
            4.072840213775635,
            4.072840213775635
        ],
        [
            1.5,
            1.649999976158142,
            1.649999976158142
        ],
        [
            3.0,
            4.072840213775635,
            4.072840213775635
        ],
        [
            5.0,
            4.072840213775635,
            4.072840213775635
        ],
        [
            1.5,
            1.649999976158142,
            1.649999976158142
        ],
        [
            1.5,
            1.649999976158142,
            1.649999976158142
        ],
        [
            1.5,
            1.649999976158142,
            1.649999976158142
        ],
        [
            3.0,
            4.072840213775635,
            4.072840213775635
        ],
        [
            1.5,
            1.649999976158142,
            1.649999976158142
        ],
        [
            3.0,
            4.0728302001953125,
            4.0728302001953125
        ],
        [
            3.0,
            4.0728302001953125,
            4.0728302001953125
        ],
        [
            3.0,
            4.113920211791992,
            4.113920211791992
        ],
        [
            3.0,
            4.113920211791992,
            4.113920211791992
        ],
        [
            3.2699999809265137,
            4.296875,
            4.296875
        ],
        [
            4.0000152587890625,
            4.0,
            4.0
        ],
        [
            3.2702014446258545,
            4.296875,
            4.296875
        ],
        [
            2.0,
            4.0728302001953125,
            4.0728302001953125
        ],
        [
            2.7899999618530273,
            2.734375,
            2.734375
        ],
        [
            2.7900002002716064,
            2.734375,
            2.734375
        ],
        [
            2.7899999618530273,
            2.734375,
            2.734375
        ]
    ]
}